eitpylab/__init__.py
eitpylab/core/__init__.py
eitpylab/core/electral_properties/Current.py
eitpylab/core/electral_properties/CurrentEnum.py
eitpylab/core/electral_properties/Voltage.py
eitpylab/core/electral_properties/VoltageEnum.py
eitpylab/core/finite_element_model/__init__.py
eitpylab/core/finite_element_model/electrode_models/electrode_hua.py
eitpylab/core/finite_element_model/finite_element_model.py
eitpylab/core/finite_element_model/parameters/uniform_rho_region.py
eitpylab/core/finite_element_model/parameters/uniform_rho_simplex.py
eitpylab/core/finite_element_model/polygons/fem_elements.py
eitpylab/core/finite_element_model/polygons/linear_tetrahedron.py
eitpylab/core/finite_element_model/polygons/linear_triangle.py
eitpylab/core/mesh_generator/__init__.py
eitpylab/core/mesh_generator/mesh_generator.py
eitpylab/core/observation_model/__init__.py
eitpylab/core/observation_model/ObservationModel.py
eitpylab/core/session/session.py
eitpylab/models/__init__.py
eitpylab/models/electral_properties_model.py
eitpylab/models/fem_model.py
eitpylab/models/forward_problem_model.py
eitpylab/utils/__init__.py
eitpylab/utils/cache_manager/cache_manager.py
eitpylab/utils/date_helper/__init__.py
eitpylab/utils/date_helper/date_now.py
eitpylab/utils/eit_paradiso_sparser.py
eitpylab/utils/interfaces/__init__.py
eitpylab/utils/interfaces/ParameterParserInterface.py
eitpylab/utils/matrix_checker.py
eitpylab/utils/metaclasses/__init__.py
eitpylab/utils/metaclasses/singleton_meta.py
eitpylab/utils/multiprocessing_cores.py
eitpylab/utils/os_path_pattern/os_path_pattern.py
eitpylab/utils/parameter_parser/__init__.py
eitpylab/utils/parameter_parser/fem_enum.py
eitpylab/utils/parameter_parser/parameter_enum.py
eitpylab/utils/parameter_parser/parameter_parser_singleton.py
eitpylab/utils/PyPardisoProject/pypardiso/__init__.py
eitpylab/utils/PyPardisoProject/pypardiso/pardiso_wrapper.py
eitpylab/utils/PyPardisoProject/pypardiso/scipy_aliases.py
eitpylab-0.1.0.dist-info/METADATA
eitpylab-0.1.0.dist-info/WHEEL
eitpylab-0.1.0.dist-info/RECORD
