Metadata-Version: 2.1
Name: eitpylab
Version: 0.1.0
Summary: 
Author: Barbara Chan Tong
Author-email: barbarachantong@gmail.com
Requires-Python: >=3.10,<3.13
Classifier: Programming Language :: Python :: 3
Classifier: Programming Language :: Python :: 3.10
Classifier: Programming Language :: Python :: 3.11
Classifier: Programming Language :: Python :: 3.12
Requires-Dist: black (>=23.9.1,<24.0.0)
Requires-Dist: matplotlib (>=3.8.2,<4.0.0)
Requires-Dist: meshio (>=5.3.4,<6.0.0)
Requires-Dist: mkdocs (>=1.5.3,<2.0.0)
Requires-Dist: mkdocs-material (>=9.5.4,<10.0.0)
Requires-Dist: mkdocstrings (>=0.24.0,<0.25.0)
Requires-Dist: mkdocstrings-python (>=1.8.0,<2.0.0)
Requires-Dist: numpy (>=1.26.0,<2.0.0)
Requires-Dist: ruamel-yaml (>=0.18.6,<0.19.0)
Requires-Dist: scipy (>=1.11.4,<2.0.0)
